{
  "title": "Michelle's Blog",
  "url": "https://example.com/",
  "language": "en",
  "description": "A blog about becoming a web developer.",
  "feed": {
    "subtitle": "with the slowest learner of all time.",
    "filename": "feed.xml",
    "path": "/feed/feed.xml",
    "id": "https://example.com/"
  },
  "jsonfeed": {
    "path": "/feed/feed.json",
    "url": "https://example.com/feed/feed.json"
  },
  "author": {
    "name": "Your Name Here",
    "email": "youremailaddress@example.com",
    "url": "https://example.com/about-me/"
  }
}
